// class version 52.0 (52)
// access flags 0x31
public final class CodeFragment {

  // compiled from: fragment.kt

  @Lkotlin/Metadata;(mv={2, 4, 0}, k=3, xi=48)

  // access flags 0x1
  public <init>()V
   L0
    ALOAD 0
    INVOKESPECIAL java/lang/Object.<init> ()V
    RETURN
   L1
    LOCALVARIABLE this LCodeFragment; L0 L1 0
    MAXSTACK = 1
    MAXLOCALS = 1

  // access flags 0x19
  public final static run()Ljava/lang/String;
  @Lorg/jetbrains/annotations/NotNull;() // invisible
   L0
    LINENUMBER 27 L0
    LDC Ljava/util/Map;.class
    GETSTATIC kotlin/reflect/KTypeProjection.Companion : Lkotlin/reflect/KTypeProjection$Companion;
    LDC Ljava/util/Set;.class
    GETSTATIC kotlin/reflect/KTypeProjection.Companion : Lkotlin/reflect/KTypeProjection$Companion;
    LDC Ljava/lang/String;.class
    INVOKESTATIC kotlin/jvm/internal/Reflection.typeOf (Ljava/lang/Class;)Lkotlin/reflect/KType;
    INVOKEVIRTUAL kotlin/reflect/KTypeProjection$Companion.covariant (Lkotlin/reflect/KType;)Lkotlin/reflect/KTypeProjection;
    INVOKESTATIC kotlin/jvm/internal/Reflection.typeOf (Ljava/lang/Class;Lkotlin/reflect/KTypeProjection;)Lkotlin/reflect/KType;
    INVOKEVIRTUAL kotlin/reflect/KTypeProjection$Companion.contravariant (Lkotlin/reflect/KType;)Lkotlin/reflect/KTypeProjection;
    GETSTATIC kotlin/reflect/KTypeProjection.Companion : Lkotlin/reflect/KTypeProjection$Companion;
    LDC LA;.class
    GETSTATIC kotlin/reflect/KTypeProjection.Companion : Lkotlin/reflect/KTypeProjection$Companion;
    GETSTATIC java/lang/Integer.TYPE : Ljava/lang/Class;
    INVOKESTATIC kotlin/jvm/internal/Reflection.typeOf (Ljava/lang/Class;)Lkotlin/reflect/KType;
    INVOKEVIRTUAL kotlin/reflect/KTypeProjection$Companion.contravariant (Lkotlin/reflect/KType;)Lkotlin/reflect/KTypeProjection;
    INVOKESTATIC kotlin/jvm/internal/Reflection.typeOf (Ljava/lang/Class;Lkotlin/reflect/KTypeProjection;)Lkotlin/reflect/KType;
    INVOKEVIRTUAL kotlin/reflect/KTypeProjection$Companion.invariant (Lkotlin/reflect/KType;)Lkotlin/reflect/KTypeProjection;
    INVOKESTATIC kotlin/jvm/internal/Reflection.typeOf (Ljava/lang/Class;Lkotlin/reflect/KTypeProjection;Lkotlin/reflect/KTypeProjection;)Lkotlin/reflect/KType;
    INVOKEVIRTUAL java/lang/Object.toString ()Ljava/lang/String;
    ARETURN
    MAXSTACK = 6
    MAXLOCALS = 0
}
