// class version 52.0 (52)
// access flags 0x31
public final class MainKt {

  // compiled from: main.kt

  @Lkotlin/Metadata;(mv={2, 4, 0}, k=2, xi=48, d1={"\u0000\u000c\n\u0000\n\u0002\u0010\u0002\n\u0000\n\u0002\u0018\u0002\u001a\u000e\u0010\u0000\u001a\u00020\u00012\u0006\u0010\u0002\u001a\u00020\u0003"}, d2={"test", "", "context", "LContext;"})

  // access flags 0x19
  public final static test(LContext;)V
    // annotable parameter count: 1 (invisible)
    @Lorg/jetbrains/annotations/NotNull;() // invisible, parameter 0
   L0
    ALOAD 0
    LDC "context"
    INVOKESTATIC kotlin/jvm/internal/Intrinsics.checkNotNullParameter (Ljava/lang/Object;Ljava/lang/String;)V
   L1
    LINENUMBER 21 L1
    NEW java/lang/StringBuilder
    DUP
    INVOKESPECIAL java/lang/StringBuilder.<init> ()V
    ALOAD 0
    INVOKEVIRTUAL Context.my_foo ()Ljava/lang/String;
    INVOKEVIRTUAL java/lang/StringBuilder.append (Ljava/lang/String;)Ljava/lang/StringBuilder;
    ALOAD 0
    INVOKEVIRTUAL Context.my_getBar ()Ljava/lang/String;
    INVOKEVIRTUAL java/lang/StringBuilder.append (Ljava/lang/String;)Ljava/lang/StringBuilder;
    INVOKEVIRTUAL java/lang/StringBuilder.toString ()Ljava/lang/String;
    POP
   L2
    LINENUMBER 22 L2
    RETURN
   L3
    LOCALVARIABLE context LContext; L0 L3 0
    MAXSTACK = 2
    MAXLOCALS = 1
}
