// class version 52.0 (52)
// access flags 0x31
public final class OperatorOfFromArrayKt {

  // compiled from: operatorOfFromArray.kt

  @Lkotlin/Metadata;(mv={2, 3, 0}, k=2, xi=48, d1={"\u0000\u0006\n\u0000\n\u0002\u0010\u0002\u001a\u0006\u0010\u0000\u001a\u00020\u0001"}, d2={"main", ""})

  // access flags 0x19
  public final static main()V
   L0
    LINENUMBER 7 L0
    ICONST_3
    ANEWARRAY java/lang/Long
    ASTORE 1
    ALOAD 1
    ICONST_0
    LCONST_1
    INVOKESTATIC java/lang/Long.valueOf (J)Ljava/lang/Long;
    AASTORE
    ALOAD 1
    ICONST_1
    LDC 2
    INVOKESTATIC java/lang/Long.valueOf (J)Ljava/lang/Long;
    AASTORE
    ALOAD 1
    ICONST_2
    LDC 3
    INVOKESTATIC java/lang/Long.valueOf (J)Ljava/lang/Long;
    AASTORE
    ALOAD 1
    ASTORE 0
   L1
    LINENUMBER 8 L1
    ICONST_3
    ANEWARRAY java/lang/Integer
    ASTORE 1
    ALOAD 1
    ICONST_0
    ICONST_1
    INVOKESTATIC java/lang/Integer.valueOf (I)Ljava/lang/Integer;
    AASTORE
    ALOAD 1
    ICONST_1
    ICONST_2
    INVOKESTATIC java/lang/Integer.valueOf (I)Ljava/lang/Integer;
    AASTORE
    ALOAD 1
    ICONST_2
    ICONST_3
    INVOKESTATIC java/lang/Integer.valueOf (I)Ljava/lang/Integer;
    AASTORE
    ALOAD 1
    INVOKESTATIC kotlin/collections/CollectionsKt.listOf ([Ljava/lang/Object;)Ljava/util/List;
    POP
   L2
    LINENUMBER 9 L2
    RETURN
   L3
    LOCALVARIABLE it [Ljava/lang/Long; L1 L3 0
    MAXSTACK = 4
    MAXLOCALS = 2

  // access flags 0x1009
  public static synthetic main([Ljava/lang/String;)V
   L0
    INVOKESTATIC OperatorOfFromArrayKt.main ()V
    RETURN
   L1
    LOCALVARIABLE args [Ljava/lang/String; L0 L1 0
    MAXSTACK = 0
    MAXLOCALS = 1
}
