// class version 52.0 (52)
// access flags 0x31
public final class CodeFragment {

  // compiled from: fragment.kt

  @Lkotlin/Metadata;(mv={2, 4, 0}, k=3, xi=48)

  // access flags 0x1
  public <init>()V
   L0
    ALOAD 0
    INVOKESPECIAL java/lang/Object.<init> ()V
    RETURN
   L1
    LOCALVARIABLE this LCodeFragment; L0 L1 0
    MAXSTACK = 1
    MAXLOCALS = 1

  // access flags 0x19
  public final static run(IIIIILX;I)I
    // annotable parameter count: 7 (invisible)
    @Lorg/jetbrains/annotations/NotNull;() // invisible, parameter 5
   L0
    ALOAD 5
    LDC "p5"
    INVOKESTATIC kotlin/jvm/internal/Intrinsics.checkNotNullParameter (Ljava/lang/Object;Ljava/lang/String;)V
   L1
    LINENUMBER 61 L1
    ILOAD 0
    BIPUSH 12
    IADD
    ISTORE 0
    ILOAD 1
    ILOAD 2
    IADD
    ILOAD 3
    ICONST_5
    IMUL
    ISTORE 3
    ILOAD 3
    ILOAD 4
    IADD
    IADD
    ALOAD 5
    INVOKEVIRTUAL X.getPropLazy ()I
    IADD
    ALOAD 5
    INVOKEVIRTUAL X.getX ()I
    IADD
    ILOAD 0
    IADD
    ILOAD 6
    IADD
    ALOAD 5
    INVOKEVIRTUAL X.getPropVar ()I
    IADD
    IRETURN
   L2
    LOCALVARIABLE p0 I L0 L2 0
    LOCALVARIABLE p1 I L0 L2 1
    LOCALVARIABLE p2 I L0 L2 2
    LOCALVARIABLE p3 I L0 L2 3
    LOCALVARIABLE p4 I L0 L2 4
    LOCALVARIABLE p5 LX; L0 L2 5
    LOCALVARIABLE p6 I L0 L2 6
    MAXSTACK = 3
    MAXLOCALS = 7
}
