// class version 52.0 (52)
// access flags 0x31
public final class CodeFragment {

  // compiled from: fragment.kt

  @Lkotlin/Metadata;(mv={2, 4, 0}, k=3, xi=48)

  // access flags 0x1
  public <init>()V
   L0
    ALOAD 0
    INVOKESPECIAL java/lang/Object.<init> ()V
    RETURN
   L1
    LOCALVARIABLE this LCodeFragment; L0 L1 0
    MAXSTACK = 1
    MAXLOCALS = 1

  // access flags 0x19
  public final static run(LContext;)Ljava/lang/String;
  @Lorg/jetbrains/annotations/NotNull;() // invisible
    // annotable parameter count: 1 (invisible)
    @Lorg/jetbrains/annotations/NotNull;() // invisible, parameter 0
   L0
    ALOAD 0
    LDC "p0"
    INVOKESTATIC kotlin/jvm/internal/Intrinsics.checkNotNullParameter (Ljava/lang/Object;Ljava/lang/String;)V
   L1
    LINENUMBER 31 L1
    NEW java/lang/StringBuilder
    DUP
    INVOKESPECIAL java/lang/StringBuilder.<init> ()V
    ALOAD 0
    INVOKEVIRTUAL Context.my_foo ()Ljava/lang/String;
    INVOKEVIRTUAL java/lang/StringBuilder.append (Ljava/lang/String;)Ljava/lang/StringBuilder;
    ALOAD 0
    INVOKEVIRTUAL Context.my_getBar ()Ljava/lang/String;
    INVOKEVIRTUAL java/lang/StringBuilder.append (Ljava/lang/String;)Ljava/lang/StringBuilder;
    INVOKEVIRTUAL java/lang/StringBuilder.toString ()Ljava/lang/String;
    ARETURN
   L2
    LOCALVARIABLE p0 LContext; L0 L2 0
    MAXSTACK = 2
    MAXLOCALS = 1
}
